{
  "updated_at": "2026-07-07 16:21",
  "tickers": [
    {
      "ticker": "AVGO",
      "price": 370.98,
      "rsi": 43.9,
      "signals": [
        {
          "type": "MA",
          "msg": "5일선 $370.48",
          "color": "pink"
        }
      ],
      "fibonacci": [
        {
          "level": 0.0,
          "price": 494.22,
          "near": false
        },
        {
          "level": 0.236,
          "price": 440.74,
          "near": false
        },
        {
          "level": 0.382,
          "price": 407.66,
          "near": false
        },
        {
          "level": 0.5,
          "price": 380.92,
          "near": false
        }
      ],
      "fib_high": 494.22,
      "fib_low": 267.62
    },
    {
      "ticker": "TSLA",
      "price": 407.4,
      "rsi": 50.9,
      "signals": [],
      "fibonacci": [
        {
          "level": 0.0,
          "price": 498.83,
          "near": false
        },
        {
          "level": 0.236,
          "price": 449.26,
          "near": false
        },
        {
          "level": 0.382,
          "price": 418.59,
          "near": false
        },
        {
          "level": 0.5,
          "price": 393.8,
          "near": false
        }
      ],
      "fib_high": 498.83,
      "fib_low": 288.77
    },
    {
      "ticker": "TEM",
      "price": 61.1,
      "rsi": 65.8,
      "signals": [],
      "fibonacci": [
        {
          "level": 0.0,
          "price": 104.32,
          "near": false
        },
        {
          "level": 0.236,
          "price": 89.55,
          "near": false
        },
        {
          "level": 0.382,
          "price": 80.41,
          "near": false
        },
        {
          "level": 0.5,
          "price": 73.02,
          "near": false
        }
      ],
      "fib_high": 104.32,
      "fib_low": 41.73
    },
    {
      "ticker": "OKLO",
      "price": 48.37,
      "rsi": 35.4,
      "signals": [],
      "fibonacci": [
        {
          "level": 0.0,
          "price": 193.84,
          "near": false
        },
        {
          "level": 0.236,
          "price": 158.69,
          "near": false
        },
        {
          "level": 0.382,
          "price": 136.94,
          "near": false
        },
        {
          "level": 0.5,
          "price": 119.36,
          "near": false
        }
      ],
      "fib_high": 193.84,
      "fib_low": 44.88
    },
    {
      "ticker": "SOXL",
      "price": 165.69,
      "rsi": 42.8,
      "signals": [],
      "fibonacci": [
        {
          "level": 0.0,
          "price": 302.0,
          "near": false
        },
        {
          "level": 0.236,
          "price": 236.05,
          "near": false
        },
        {
          "level": 0.382,
          "price": 195.26,
          "near": false
        },
        {
          "level": 0.5,
          "price": 162.28,
          "near": false
        }
      ],
      "fib_high": 302.0,
      "fib_low": 22.56
    },
    {
      "ticker": "TQQQ",
      "price": 72.96,
      "rsi": 46.4,
      "signals": [],
      "fibonacci": [
        {
          "level": 0.0,
          "price": 87.89,
          "near": false
        },
        {
          "level": 0.236,
          "price": 75.93,
          "near": false
        },
        {
          "level": 0.382,
          "price": 68.54,
          "near": false
        },
        {
          "level": 0.5,
          "price": 62.56,
          "near": false
        }
      ],
      "fib_high": 87.89,
      "fib_low": 37.23
    },
    {
      "ticker": "QCOM",
      "price": 183.09,
      "rsi": 42.1,
      "signals": [],
      "fibonacci": [
        {
          "level": 0.0,
          "price": 259.92,
          "near": false
        },
        {
          "level": 0.236,
          "price": 227.37,
          "near": false
        },
        {
          "level": 0.382,
          "price": 207.23,
          "near": false
        },
        {
          "level": 0.5,
          "price": 190.96,
          "near": false
        }
      ],
      "fib_high": 259.92,
      "fib_low": 121.99
    },
    {
      "ticker": "BMNR",
      "price": 15.44,
      "rsi": 46.7,
      "signals": [],
      "fibonacci": [
        {
          "level": 0.0,
          "price": 134.44,
          "near": false
        },
        {
          "level": 0.236,
          "price": 105.73,
          "near": false
        },
        {
          "level": 0.382,
          "price": 87.97,
          "near": false
        },
        {
          "level": 0.5,
          "price": 73.62,
          "near": false
        }
      ],
      "fib_high": 134.44,
      "fib_low": 12.8
    },
    {
      "ticker": "PLTR",
      "price": 135.7,
      "rsi": 56.9,
      "signals": [],
      "fibonacci": [
        {
          "level": 0.0,
          "price": 207.52,
          "near": false
        },
        {
          "level": 0.236,
          "price": 183.65,
          "near": false
        },
        {
          "level": 0.382,
          "price": 168.88,
          "near": false
        },
        {
          "level": 0.5,
          "price": 156.95,
          "near": false
        }
      ],
      "fib_high": 207.52,
      "fib_low": 106.37
    },
    {
      "ticker": "GOOGL",
      "price": 368.67,
      "rsi": 55.0,
      "signals": [],
      "fibonacci": [
        {
          "level": 0.0,
          "price": 408.37,
          "near": false
        },
        {
          "level": 0.236,
          "price": 352.65,
          "near": false
        },
        {
          "level": 0.382,
          "price": 318.18,
          "near": false
        },
        {
          "level": 0.5,
          "price": 290.32,
          "near": false
        }
      ],
      "fib_high": 408.37,
      "fib_low": 172.28
    }
  ],
  "vix": {
    "vix": 16.0,
    "prev": 15.57,
    "change": 0.43
  },
  "fear_greed": {
    "score": 42,
    "rating": "fear",
    "rating_kr": "공포"
  }
}